XEdu/__init__.py
XEdu/version.py
XEdu/LLM/__init__.py
XEdu/LLM/client.py
XEdu/LLM/utils.py
XEdu/LLM/llms/__init__.py
XEdu/LLM/llms/base.py
XEdu/LLM/llms/baseurl.py
XEdu/LLM/llms/deepseek.py
XEdu/LLM/llms/ernie.py
XEdu/LLM/llms/glm.py
XEdu/LLM/llms/gradioapi.py
XEdu/LLM/llms/moonshot.py
XEdu/LLM/llms/openrouter.py
XEdu/LLM/llms/qwen.py
XEdu/examples/__init__.py
XEdu/examples/demo.py
XEdu/hub/BaseDeploy.py
XEdu/hub/__init__.py
XEdu/hub/datatset_class.py
XEdu/hub/errorcode.py
XEdu/hub/workflow.py
XEdu/hub/BaseDT/__init__.py
XEdu/hub/BaseDT/data.py
XEdu/hub/BaseDT/data_image.py
XEdu/hub/BaseDT/dataset.py
XEdu/hub/BaseDT/io.py
XEdu/hub/BaseDT/plot.py
XEdu/hub/BaseDT/utils.py
XEdu/hub/models/__init__.py
XEdu/hub/models/clap.py
XEdu/hub/models/depth_anything.py
XEdu/hub/models/efficientVIT_sam.py
XEdu/hub/tokenizer/__init__.py
XEdu/hub/tokenizer/clip_tokenizer.py
XEdu/hub/tokenizer/qa_squadprocess.py
XEdu/hub/tokenizer/qa_tokenizer.py
XEdu/utils/__init__.py
XEdu/utils/utils.py
xedu_python-2.0.0.dist-info/METADATA
xedu_python-2.0.0.dist-info/WHEEL
xedu_python-2.0.0.dist-info/entry_points.txt
xedu_python-2.0.0.dist-info/top_level.txt
xedu_python-2.0.0.dist-info/zip-safe
xedu_python-2.0.0.dist-info/RECORD
