Metadata-Version: 2.1
Name: xedu-python
Version: 2.0.0
Summary: XEduPro Hub and LLM
Home-page: https://github.com/XEduPro/XEdu-python
Author: XEduPro
Author-email: easonqys@foxmail.com
License: MIT License
Requires-Python: >=3.6
Requires-Dist: matplotlib
Requires-Dist: opencv-python >=4.1.2.30
Requires-Dist: onnx
Requires-Dist: onnxruntime <1.16.0
Requires-Dist: pillow <=9.5.0
Requires-Dist: ftfy
Requires-Dist: regex
Requires-Dist: tqdm
Requires-Dist: requests
Requires-Dist: soundfile
